actiwatch/__init__.py
actiwatch/__version__.py
actiwatch/analysis.py
actiwatch/file_import.py
actiwatch/helpers.py
actiwatch/sleep_processing.py
actiwatch/watch.py
actiwatch-0.2.0.dist-info/METADATA
actiwatch-0.2.0.dist-info/RECORD
actiwatch-0.2.0.dist-info/WHEEL
actiwatch-0.2.0.dist-info/top_level.txt
tests/__init__.py
tests/context.py
tests/test_DST.py
tests/test_analysis.py
tests/test_file_import.py
tests/test_helpers.py
tests/test_sleep_processing.py
