Metadata-Version: 2.1
Name: actiwatch
Version: 0.2.0
Summary: Actiwatch is a Python module built for interacting with Philips Actiwatch actigraphy devices.
Home-page: UNKNOWN
Author: Ryan Opel
Author-email: ryan.a.opel@gmail.com
License: GNU GENERAL PUBLIC LICENSE
Requires-Dist: pandas (>=0.23.0)
Requires-Dist: astral (==1.6.1)
Requires-Dist: numpy (==1.15.1)
